{
  "Version": "3.3.0", 
  "Began": "Mon Dec  9 20:18:09 2024", 
  "Command line": "ior -a POSIX -w -r -t 4m -b 4m -s 20 -e -F -o ///rcfs/projects/chess/tang584/iortest_5gb/pior_4m_5gb_n64_2.bin -O summaryFormat=JSON -O summaryFile=pior_4m_5gb_n64_2.json", 
  "Machine": "Linux dc193.local", 
  "tests": [
    {
    "TestID": 0, 
    "StartTime": "Mon Dec  9 20:18:09 2024"    , "Path": "/rcfs/projects/chess/tang584/iortest_5gb","Capacity": "4579.0 TiB", "Used Capacity": "80.8%","Inodes": "0.0 Mi", "Used Inodes" : "-nan%"
, 
    "Parameters": {
      "testID": 0, 
      "refnum": 0, 
      "api": "POSIX", 
      "platform": "dc193.local(Linux)", 
      "testFileName": "///rcfs/projects/chess/tang584/iortest_5gb/pior_4m_5gb_n64_2.bin", 
      "hintsFileName": "(null)", 
      "deadlineForStonewall": 0, 
      "stoneWallingWearOut": 0, 
      "maxTimeDuration": 0, 
      "outlierThreshold": 0, 
      "options": "(null)", 
      "dryRun": 0, 
      "nodes": 8, 
      "memoryPerTask": 0, 
      "memoryPerNode": 0, 
      "tasksPerNode": 8, 
      "repetitions": 1, 
      "multiFile": 0, 
      "interTestDelay": 0, 
      "fsync": 1, 
      "fsyncperwrite": 0, 
      "useExistingTestFile": 0, 
      "showHints": 0, 
      "uniqueDir": 0, 
      "individualDataSets": 0, 
      "singleXferAttempt": 0, 
      "readFile": 1, 
      "writeFile": 1, 
      "filePerProc": 1, 
      "reorderTasks": 0, 
      "reorderTasksRandom": 0, 
      "reorderTasksRandomSeed": 0, 
      "randomOffset": 0, 
      "checkWrite": 0, 
      "checkRead": 0, 
      "preallocate": 0, 
      "useFileView": 0, 
      "setAlignment": 1, 
      "storeFileOffset": 0, 
      "useSharedFilePointer": 0, 
      "useStridedDatatype": 0, 
      "keepFile": 0, 
      "keepFileWithError": 0, 
      "quitOnError": 0, 
      "verbose": 0, 
      "data packet type": "g", 
      "setTimeStampSignature/incompressibleSeed": 0, 
      "collective": 0, 
      "segmentCount": 20, 
      "transferSize": 4194304, 
      "blockSize": 4194304
    }
, 
    "Options": {
      "api": "POSIX", 
      "apiVersion": "", 
      "test filename": "///rcfs/projects/chess/tang584/iortest_5gb/pior_4m_5gb_n64_2.bin", 
      "access": "file-per-process", 
      "type": "independent", 
      "segments": 20, 
      "ordering in a file": "sequential", 
      "ordering inter file": "no tasks offsets", 
      "nodes": 8, 
      "tasks": 64, 
      "clients per node": 8, 
      "repetitions": 1, 
      "xfersize": "4 MiB", 
      "blocksize": "4 MiB", 
      "aggregate filesize": "5 GiB"
    }
, 
    "Results": [
      [             {
        "access": "write", 
        "bwMiB": 26995.3736, 
        "blockKiB": 4096.0000, 
        "xferKiB": 4096.0000, 
        "iops": 6804.9392, 
        "latency": 0.1386, 
        "openTime": 0.0107, 
        "wrRdTime": 0.1881, 
        "closeTime": 0.0608, 
        "totalTime": 0.1897
      }
, 
            {
        "access": "read", 
        "bwMiB": 28355.8282, 
        "blockKiB": 4096.0000, 
        "xferKiB": 4096.0000, 
        "iops": 7141.1542, 
        "latency": 0.1364, 
        "openTime": 0.0025, 
        "wrRdTime": 0.1792, 
        "closeTime": 0.1168, 
        "totalTime": 0.1806
      }
, 
            {
        "access": "remove", 
        "totalTime": 0.0105
      }
]
]
, 
  "max": {
    "writeMiB": 26995.3736, 
    "writeMB": 28306.7009, 
    "readMiB": 28355.8282, 
    "readMB": 29733.2409
  }

}
]
, 
"summary": [
{
  "operation": "write", 
  "API": "POSIX", 
  "TestID": 0, 
  "ReferenceNumber": 0, 
  "segmentCount": 20, 
  "blockSize": 4194304, 
  "transferSize": 4194304, 
  "numTasks": 64, 
  "tasksPerNode": 8, 
  "repetitions": 1, 
  "filePerProc": 1, 
  "reorderTasks": 0, 
  "taskPerNodeOffset": 1, 
  "reorderTasksRandom": 0, 
  "reorderTasksRandomSeed": 0, 
  "segmentCount": 20, 
  "blockSize": 4194304, 
  "transferSize": 4194304, 
  "bwMaxMIB": 26995.3736, 
  "bwMinMIB": 26995.3736, 
  "bwMeanMIB": 26995.3736, 
  "bwStdMIB": 0.0000, 
  "OPsMax": 6748.8434, 
  "OPsMin": 6748.8434, 
  "OPsMean": 6748.8434, 
  "OPsSD": 0.0000, 
  "MeanTime": 0.1897, 
  "xsizeMiB": 5120.0000
}
, 
{
  "operation": "read", 
  "API": "POSIX", 
  "TestID": 0, 
  "ReferenceNumber": 0, 
  "segmentCount": 20, 
  "blockSize": 4194304, 
  "transferSize": 4194304, 
  "numTasks": 64, 
  "tasksPerNode": 8, 
  "repetitions": 1, 
  "filePerProc": 1, 
  "reorderTasks": 0, 
  "taskPerNodeOffset": 1, 
  "reorderTasksRandom": 0, 
  "reorderTasksRandomSeed": 0, 
  "segmentCount": 20, 
  "blockSize": 4194304, 
  "transferSize": 4194304, 
  "bwMaxMIB": 28355.8282, 
  "bwMinMIB": 28355.8282, 
  "bwMeanMIB": 28355.8282, 
  "bwStdMIB": 0.0000, 
  "OPsMax": 7088.9571, 
  "OPsMin": 7088.9571, 
  "OPsMean": 7088.9571, 
  "OPsSD": 0.0000, 
  "MeanTime": 0.1806, 
  "xsizeMiB": 5120.0000
}
]
, 
"Finished": "Mon Dec  9 20:18:09 2024"
}
