{
  "Version": "3.3.0", 
  "Began": "Mon Dec 16 18:50:34 2024", 
  "Command line": "/qfs/people/tang584/spack/opt/spack/linux-centos7-zen2/gcc-9.1.0/ior-3.3.0-5vckblqh6knqounapczzqzwozq2ueq4q/bin/ior -a POSIX -w -r -t 256m -b 256m -s 12 -e -F -o ///scratch/tang584/iortest_100gb/pior_256m_100gb_n32_2.bin -O summaryFormat=JSON -O summaryFile=pior_256m_100gb_n32_2.json", 
  "Machine": "Linux dc084.local", 
  "tests": [
    {
    "TestID": 0, 
    "StartTime": "Mon Dec 16 18:50:34 2024"    , "Path": "/scratch/tang584/iortest_100gb","Capacity": "476.7 GiB", "Used Capacity": "0.0%","Inodes": "238.5 Mi", "Used Inodes" : "0.0%"
, 
    "Parameters": {
      "testID": 0, 
      "refnum": 0, 
      "api": "POSIX", 
      "platform": "dc084.local(Linux)", 
      "testFileName": "///scratch/tang584/iortest_100gb/pior_256m_100gb_n32_2.bin", 
      "hintsFileName": "(null)", 
      "deadlineForStonewall": 0, 
      "stoneWallingWearOut": 0, 
      "maxTimeDuration": 0, 
      "outlierThreshold": 0, 
      "options": "(null)", 
      "dryRun": 0, 
      "nodes": 4, 
      "memoryPerTask": 0, 
      "memoryPerNode": 0, 
      "tasksPerNode": 8, 
      "repetitions": 1, 
      "multiFile": 0, 
      "interTestDelay": 0, 
      "fsync": 1, 
      "fsyncperwrite": 0, 
      "useExistingTestFile": 0, 
      "showHints": 0, 
      "uniqueDir": 0, 
      "individualDataSets": 0, 
      "singleXferAttempt": 0, 
      "readFile": 1, 
      "writeFile": 1, 
      "filePerProc": 1, 
      "reorderTasks": 0, 
      "reorderTasksRandom": 0, 
      "reorderTasksRandomSeed": 0, 
      "randomOffset": 0, 
      "checkWrite": 0, 
      "checkRead": 0, 
      "preallocate": 0, 
      "useFileView": 0, 
      "setAlignment": 1, 
      "storeFileOffset": 0, 
      "useSharedFilePointer": 0, 
      "useStridedDatatype": 0, 
      "keepFile": 0, 
      "keepFileWithError": 0, 
      "quitOnError": 0, 
      "verbose": 0, 
      "data packet type": "g", 
      "setTimeStampSignature/incompressibleSeed": 0, 
      "collective": 0, 
      "segmentCount": 12, 
      "transferSize": 268435456, 
      "blockSize": 268435456
    }
, 
    "Options": {
      "api": "POSIX", 
      "apiVersion": "", 
      "test filename": "///scratch/tang584/iortest_100gb/pior_256m_100gb_n32_2.bin", 
      "access": "file-per-process", 
      "type": "independent", 
      "segments": 12, 
      "ordering in a file": "sequential", 
      "ordering inter file": "no tasks offsets", 
      "nodes": 4, 
      "tasks": 32, 
      "clients per node": 8, 
      "repetitions": 1, 
      "xfersize": "256 MiB", 
      "blocksize": "256 MiB", 
      "aggregate filesize": "96 GiB"
    }
, 
    "Results": [
      [             {
        "access": "write", 
        "bwMiB": 1485.2205, 
        "blockKiB": 262144.0000, 
        "xferKiB": 262144.0000, 
        "iops": 5.8017, 
        "latency": 65.8711, 
        "openTime": 0.0006, 
        "wrRdTime": 66.1880, 
        "closeTime": 33.7852, 
        "totalTime": 66.1882
      }
, 
            {
        "access": "read", 
        "bwMiB": 189109.9137, 
        "blockKiB": 262144.0000, 
        "xferKiB": 262144.0000, 
        "iops": 738.7310, 
        "latency": 0.5117, 
        "openTime": 0.0001, 
        "wrRdTime": 0.5198, 
        "closeTime": 0.0373, 
        "totalTime": 0.5198
      }
, 
            {
        "access": "remove", 
        "totalTime": 0.3751
      }
]
]
, 
  "max": {
    "writeMiB": 1485.2205, 
    "writeMB": 1557.3666, 
    "readMiB": 189109.9137, 
    "readMB": 198296.1169
  }

}
]
, 
"summary": [
{
  "operation": "write", 
  "API": "POSIX", 
  "TestID": 0, 
  "ReferenceNumber": 0, 
  "segmentCount": 12, 
  "blockSize": 268435456, 
  "transferSize": 268435456, 
  "numTasks": 32, 
  "tasksPerNode": 8, 
  "repetitions": 1, 
  "filePerProc": 1, 
  "reorderTasks": 0, 
  "taskPerNodeOffset": 1, 
  "reorderTasksRandom": 0, 
  "reorderTasksRandomSeed": 0, 
  "segmentCount": 12, 
  "blockSize": 268435456, 
  "transferSize": 268435456, 
  "bwMaxMIB": 1485.2205, 
  "bwMinMIB": 1485.2205, 
  "bwMeanMIB": 1485.2205, 
  "bwStdMIB": 0.0000, 
  "OPsMax": 5.8016, 
  "OPsMin": 5.8016, 
  "OPsMean": 5.8016, 
  "OPsSD": 0.0000, 
  "MeanTime": 66.1882, 
  "xsizeMiB": 98304.0000
}
, 
{
  "operation": "read", 
  "API": "POSIX", 
  "TestID": 0, 
  "ReferenceNumber": 0, 
  "segmentCount": 12, 
  "blockSize": 268435456, 
  "transferSize": 268435456, 
  "numTasks": 32, 
  "tasksPerNode": 8, 
  "repetitions": 1, 
  "filePerProc": 1, 
  "reorderTasks": 0, 
  "taskPerNodeOffset": 1, 
  "reorderTasksRandom": 0, 
  "reorderTasksRandomSeed": 0, 
  "segmentCount": 12, 
  "blockSize": 268435456, 
  "transferSize": 268435456, 
  "bwMaxMIB": 189109.9137, 
  "bwMinMIB": 189109.9137, 
  "bwMeanMIB": 189109.9137, 
  "bwStdMIB": 0.0000, 
  "OPsMax": 738.7106, 
  "OPsMin": 738.7106, 
  "OPsMean": 738.7106, 
  "OPsSD": 0.0000, 
  "MeanTime": 0.5198, 
  "xsizeMiB": 98304.0000
}
]
, 
"Finished": "Mon Dec 16 18:51:41 2024"
}
