{
  "Version": "3.3.0", 
  "Began": "Mon Dec 16 14:58:10 2024", 
  "Command line": "/qfs/people/tang584/spack/opt/spack/linux-centos7-zen2/gcc-9.1.0/ior-3.3.0-5vckblqh6knqounapczzqzwozq2ueq4q/bin/ior -a POSIX -w -r -t 4m -b 4m -s 80 -e -F -o ///scratch/tang584/iortest_5gb/pior_4m_5gb_n16_2.bin -O summaryFormat=JSON -O summaryFile=pior_4m_5gb_n16_2.json", 
  "Machine": "Linux dc084.local", 
  "tests": [
    {
    "TestID": 0, 
    "StartTime": "Mon Dec 16 14:58:10 2024"    , "Path": "/scratch/tang584/iortest_5gb","Capacity": "476.7 GiB", "Used Capacity": "0.0%","Inodes": "238.5 Mi", "Used Inodes" : "0.0%"
, 
    "Parameters": {
      "testID": 0, 
      "refnum": 0, 
      "api": "POSIX", 
      "platform": "dc084.local(Linux)", 
      "testFileName": "///scratch/tang584/iortest_5gb/pior_4m_5gb_n16_2.bin", 
      "hintsFileName": "(null)", 
      "deadlineForStonewall": 0, 
      "stoneWallingWearOut": 0, 
      "maxTimeDuration": 0, 
      "outlierThreshold": 0, 
      "options": "(null)", 
      "dryRun": 0, 
      "nodes": 4, 
      "memoryPerTask": 0, 
      "memoryPerNode": 0, 
      "tasksPerNode": 4, 
      "repetitions": 1, 
      "multiFile": 0, 
      "interTestDelay": 0, 
      "fsync": 1, 
      "fsyncperwrite": 0, 
      "useExistingTestFile": 0, 
      "showHints": 0, 
      "uniqueDir": 0, 
      "individualDataSets": 0, 
      "singleXferAttempt": 0, 
      "readFile": 1, 
      "writeFile": 1, 
      "filePerProc": 1, 
      "reorderTasks": 0, 
      "reorderTasksRandom": 0, 
      "reorderTasksRandomSeed": 0, 
      "randomOffset": 0, 
      "checkWrite": 0, 
      "checkRead": 0, 
      "preallocate": 0, 
      "useFileView": 0, 
      "setAlignment": 1, 
      "storeFileOffset": 0, 
      "useSharedFilePointer": 0, 
      "useStridedDatatype": 0, 
      "keepFile": 0, 
      "keepFileWithError": 0, 
      "quitOnError": 0, 
      "verbose": 0, 
      "data packet type": "g", 
      "setTimeStampSignature/incompressibleSeed": 0, 
      "collective": 0, 
      "segmentCount": 80, 
      "transferSize": 4194304, 
      "blockSize": 4194304
    }
, 
    "Options": {
      "api": "POSIX", 
      "apiVersion": "", 
      "test filename": "///scratch/tang584/iortest_5gb/pior_4m_5gb_n16_2.bin", 
      "access": "file-per-process", 
      "type": "independent", 
      "segments": 80, 
      "ordering in a file": "sequential", 
      "ordering inter file": "no tasks offsets", 
      "nodes": 4, 
      "tasks": 16, 
      "clients per node": 4, 
      "repetitions": 1, 
      "xfersize": "4 MiB", 
      "blocksize": "4 MiB", 
      "aggregate filesize": "5 GiB"
    }
, 
    "Results": [
      [             {
        "access": "write", 
        "bwMiB": 4355.7726, 
        "blockKiB": 4096.0000, 
        "xferKiB": 4096.0000, 
        "iops": 1089.0789, 
        "latency": 0.9580, 
        "openTime": 0.0003, 
        "wrRdTime": 1.1753, 
        "closeTime": 0.4792, 
        "totalTime": 1.1755
      }
, 
            {
        "access": "read", 
        "bwMiB": 52519.3071, 
        "blockKiB": 4096.0000, 
        "xferKiB": 4096.0000, 
        "iops": 13131.8259, 
        "latency": 0.0515, 
        "openTime": 0.0000, 
        "wrRdTime": 0.0975, 
        "closeTime": 0.0624, 
        "totalTime": 0.0975
      }
, 
            {
        "access": "remove", 
        "totalTime": 0.0740
      }
]
]
, 
  "max": {
    "writeMiB": 4355.7726, 
    "writeMB": 4567.3586, 
    "readMiB": 52519.3071, 
    "readMB": 55070.4849
  }

}
]
, 
"summary": [
{
  "operation": "write", 
  "API": "POSIX", 
  "TestID": 0, 
  "ReferenceNumber": 0, 
  "segmentCount": 80, 
  "blockSize": 4194304, 
  "transferSize": 4194304, 
  "numTasks": 16, 
  "tasksPerNode": 4, 
  "repetitions": 1, 
  "filePerProc": 1, 
  "reorderTasks": 0, 
  "taskPerNodeOffset": 1, 
  "reorderTasksRandom": 0, 
  "reorderTasksRandomSeed": 0, 
  "segmentCount": 80, 
  "blockSize": 4194304, 
  "transferSize": 4194304, 
  "bwMaxMIB": 4355.7726, 
  "bwMinMIB": 4355.7726, 
  "bwMeanMIB": 4355.7726, 
  "bwStdMIB": 0.0000, 
  "OPsMax": 1088.9431, 
  "OPsMin": 1088.9431, 
  "OPsMean": 1088.9431, 
  "OPsSD": 0.0000, 
  "MeanTime": 1.1755, 
  "xsizeMiB": 5120.0000
}
, 
{
  "operation": "read", 
  "API": "POSIX", 
  "TestID": 0, 
  "ReferenceNumber": 0, 
  "segmentCount": 80, 
  "blockSize": 4194304, 
  "transferSize": 4194304, 
  "numTasks": 16, 
  "tasksPerNode": 4, 
  "repetitions": 1, 
  "filePerProc": 1, 
  "reorderTasks": 0, 
  "taskPerNodeOffset": 1, 
  "reorderTasksRandom": 0, 
  "reorderTasksRandomSeed": 0, 
  "segmentCount": 80, 
  "blockSize": 4194304, 
  "transferSize": 4194304, 
  "bwMaxMIB": 52519.3071, 
  "bwMinMIB": 52519.3071, 
  "bwMeanMIB": 52519.3071, 
  "bwStdMIB": 0.0000, 
  "OPsMax": 13129.8268, 
  "OPsMin": 13129.8268, 
  "OPsMean": 13129.8268, 
  "OPsSD": 0.0000, 
  "MeanTime": 0.0975, 
  "xsizeMiB": 5120.0000
}
]
, 
"Finished": "Mon Dec 16 14:58:12 2024"
}
