{
  "Version": "3.3.0", 
  "Began": "Fri May  2 00:52:03 2025", 
  "Command line": "ior -a POSIX -w -r -t 16m -b 16m -s 20 -e -F -o /dev/shm/tang584//qfs/projects/datamesh/tang584/linux_resource_detect/io_test/iortest_5gb/pior_16m_5gb_n16_1.bin -O summaryFormat=JSON -O summaryFile=pior_16m_5gb_n16_1.json", 
  "Machine": "Linux dc115.local", 
  "tests": [
    {
    "TestID": 0, 
    "StartTime": "Fri May  2 00:52:03 2025"    , "Path": "/dev/shm/tang584/qfs/projects/datamesh/tang584/linux_resource_detect/io_test/iortest_5gb","Capacity": "125.8 GiB", "Used Capacity": "0.0%","Inodes": "31.5 Mi", "Used Inodes" : "0.0%"
, 
    "Parameters": {
      "testID": 0, 
      "refnum": 0, 
      "api": "POSIX", 
      "platform": "dc115.local(Linux)", 
      "testFileName": "/dev/shm/tang584//qfs/projects/datamesh/tang584/linux_resource_detect/io_test/iortest_5gb/pior_16m_5gb_n16_1.bin", 
      "hintsFileName": "(null)", 
      "deadlineForStonewall": 0, 
      "stoneWallingWearOut": 0, 
      "maxTimeDuration": 0, 
      "outlierThreshold": 0, 
      "options": "(null)", 
      "dryRun": 0, 
      "nodes": 2, 
      "memoryPerTask": 0, 
      "memoryPerNode": 0, 
      "tasksPerNode": 8, 
      "repetitions": 1, 
      "multiFile": 0, 
      "interTestDelay": 0, 
      "fsync": 1, 
      "fsyncperwrite": 0, 
      "useExistingTestFile": 0, 
      "showHints": 0, 
      "uniqueDir": 0, 
      "individualDataSets": 0, 
      "singleXferAttempt": 0, 
      "readFile": 1, 
      "writeFile": 1, 
      "filePerProc": 1, 
      "reorderTasks": 0, 
      "reorderTasksRandom": 0, 
      "reorderTasksRandomSeed": 0, 
      "randomOffset": 0, 
      "checkWrite": 0, 
      "checkRead": 0, 
      "preallocate": 0, 
      "useFileView": 0, 
      "setAlignment": 1, 
      "storeFileOffset": 0, 
      "useSharedFilePointer": 0, 
      "useStridedDatatype": 0, 
      "keepFile": 0, 
      "keepFileWithError": 0, 
      "quitOnError": 0, 
      "verbose": 0, 
      "data packet type": "g", 
      "setTimeStampSignature/incompressibleSeed": 0, 
      "collective": 0, 
      "segmentCount": 20, 
      "transferSize": 16777216, 
      "blockSize": 16777216
    }
, 
    "Options": {
      "api": "POSIX", 
      "apiVersion": "", 
      "test filename": "/dev/shm/tang584//qfs/projects/datamesh/tang584/linux_resource_detect/io_test/iortest_5gb/pior_16m_5gb_n16_1.bin", 
      "access": "file-per-process", 
      "type": "independent", 
      "segments": 20, 
      "ordering in a file": "sequential", 
      "ordering inter file": "no tasks offsets", 
      "nodes": 2, 
      "tasks": 16, 
      "clients per node": 8, 
      "repetitions": 1, 
      "xfersize": "16 MiB", 
      "blocksize": "16 MiB", 
      "aggregate filesize": "5 GiB"
    }
, 
    "Results": [
      [             {
        "access": "write", 
        "bwMiB": 29575.6824, 
        "blockKiB": 16384.0000, 
        "xferKiB": 16384.0000, 
        "iops": 1848.8079, 
        "latency": 0.1034, 
        "openTime": 0.0001, 
        "wrRdTime": 0.1731, 
        "closeTime": 0.0696, 
        "totalTime": 0.1731
      }
, 
            {
        "access": "read", 
        "bwMiB": 31679.7857, 
        "blockKiB": 16384.0000, 
        "xferKiB": 16384.0000, 
        "iops": 1980.0928, 
        "latency": 0.0712, 
        "openTime": 0.0000, 
        "wrRdTime": 0.1616, 
        "closeTime": 0.0904, 
        "totalTime": 0.1616
      }
, 
            {
        "access": "remove", 
        "totalTime": 0.0692
      }
]
]
, 
  "max": {
    "writeMiB": 29575.6824, 
    "writeMB": 31012.3508, 
    "readMiB": 31679.7857, 
    "readMB": 33218.6629
  }

}
]
, 
"summary": [
{
  "operation": "write", 
  "API": "POSIX", 
  "TestID": 0, 
  "ReferenceNumber": 0, 
  "segmentCount": 20, 
  "blockSize": 16777216, 
  "transferSize": 16777216, 
  "numTasks": 16, 
  "tasksPerNode": 8, 
  "repetitions": 1, 
  "filePerProc": 1, 
  "reorderTasks": 0, 
  "taskPerNodeOffset": 1, 
  "reorderTasksRandom": 0, 
  "reorderTasksRandomSeed": 0, 
  "segmentCount": 20, 
  "blockSize": 16777216, 
  "transferSize": 16777216, 
  "bwMaxMIB": 29575.6824, 
  "bwMinMIB": 29575.6824, 
  "bwMeanMIB": 29575.6824, 
  "bwStdMIB": 0.0000, 
  "OPsMax": 1848.4802, 
  "OPsMin": 1848.4802, 
  "OPsMean": 1848.4802, 
  "OPsSD": 0.0000, 
  "MeanTime": 0.1731, 
  "xsizeMiB": 5120.0000
}
, 
{
  "operation": "read", 
  "API": "POSIX", 
  "TestID": 0, 
  "ReferenceNumber": 0, 
  "segmentCount": 20, 
  "blockSize": 16777216, 
  "transferSize": 16777216, 
  "numTasks": 16, 
  "tasksPerNode": 8, 
  "repetitions": 1, 
  "filePerProc": 1, 
  "reorderTasks": 0, 
  "taskPerNodeOffset": 1, 
  "reorderTasksRandom": 0, 
  "reorderTasksRandomSeed": 0, 
  "segmentCount": 20, 
  "blockSize": 16777216, 
  "transferSize": 16777216, 
  "bwMaxMIB": 31679.7857, 
  "bwMinMIB": 31679.7857, 
  "bwMeanMIB": 31679.7857, 
  "bwStdMIB": 0.0000, 
  "OPsMax": 1979.9866, 
  "OPsMin": 1979.9866, 
  "OPsMean": 1979.9866, 
  "OPsSD": 0.0000, 
  "MeanTime": 0.1616, 
  "xsizeMiB": 5120.0000
}
]
, 
"Finished": "Fri May  2 00:52:04 2025"
}
