{
  "Version": "3.3.0", 
  "Began": "Fri May  2 02:33:10 2025", 
  "Command line": "ior -a POSIX -w -r -t 16m -b 16m -s 1 -e -F -o /dev/shm/tang584//qfs/projects/datamesh/tang584/linux_resource_detect/io_test/iortest_5gb/pior_s_16m_5gb_n256_3.bin -O summaryFormat=JSON -O summaryFile=pior_s_16m_5gb_n256_3.json", 
  "Machine": "Linux dc038.local", 
  "tests": [
    {
    "TestID": 0, 
    "StartTime": "Fri May  2 02:33:10 2025"    , "Path": "/dev/shm/tang584/qfs/projects/datamesh/tang584/linux_resource_detect/io_test/iortest_5gb","Capacity": "125.8 GiB", "Used Capacity": "0.2%","Inodes": "31.4 Mi", "Used Inodes" : "0.0%"
, 
    "Parameters": {
      "testID": 0, 
      "refnum": 0, 
      "api": "POSIX", 
      "platform": "dc038.local(Linux)", 
      "testFileName": "/dev/shm/tang584//qfs/projects/datamesh/tang584/linux_resource_detect/io_test/iortest_5gb/pior_s_16m_5gb_n256_3.bin", 
      "hintsFileName": "(null)", 
      "deadlineForStonewall": 0, 
      "stoneWallingWearOut": 0, 
      "maxTimeDuration": 0, 
      "outlierThreshold": 0, 
      "options": "(null)", 
      "dryRun": 0, 
      "nodes": 4, 
      "memoryPerTask": 0, 
      "memoryPerNode": 0, 
      "tasksPerNode": 64, 
      "repetitions": 1, 
      "multiFile": 0, 
      "interTestDelay": 0, 
      "fsync": 1, 
      "fsyncperwrite": 0, 
      "useExistingTestFile": 0, 
      "showHints": 0, 
      "uniqueDir": 0, 
      "individualDataSets": 0, 
      "singleXferAttempt": 0, 
      "readFile": 1, 
      "writeFile": 1, 
      "filePerProc": 1, 
      "reorderTasks": 0, 
      "reorderTasksRandom": 0, 
      "reorderTasksRandomSeed": 0, 
      "randomOffset": 0, 
      "checkWrite": 0, 
      "checkRead": 0, 
      "preallocate": 0, 
      "useFileView": 0, 
      "setAlignment": 1, 
      "storeFileOffset": 0, 
      "useSharedFilePointer": 0, 
      "useStridedDatatype": 0, 
      "keepFile": 0, 
      "keepFileWithError": 0, 
      "quitOnError": 0, 
      "verbose": 0, 
      "data packet type": "g", 
      "setTimeStampSignature/incompressibleSeed": 0, 
      "collective": 0, 
      "segmentCount": 1, 
      "transferSize": 16777216, 
      "blockSize": 16777216
    }
, 
    "Options": {
      "api": "POSIX", 
      "apiVersion": "", 
      "test filename": "/dev/shm/tang584//qfs/projects/datamesh/tang584/linux_resource_detect/io_test/iortest_5gb/pior_s_16m_5gb_n256_3.bin", 
      "access": "file-per-process", 
      "type": "independent", 
      "segments": 1, 
      "ordering in a file": "sequential", 
      "ordering inter file": "no tasks offsets", 
      "nodes": 4, 
      "tasks": 256, 
      "clients per node": 64, 
      "repetitions": 1, 
      "xfersize": "16 MiB", 
      "blocksize": "16 MiB", 
      "aggregate filesize": "4 GiB"
    }
, 
    "Results": [
      [             {
        "access": "write", 
        "bwMiB": 113445.5902, 
        "blockKiB": 16384.0000, 
        "xferKiB": 16384.0000, 
        "iops": 7150.3710, 
        "latency": 0.0218, 
        "openTime": 0.0307, 
        "wrRdTime": 0.0358, 
        "closeTime": 0.0182, 
        "totalTime": 0.0361
      }
, 
            {
        "access": "read", 
        "bwMiB": 116857.1487, 
        "blockKiB": 16384.0000, 
        "xferKiB": 16384.0000, 
        "iops": 7305.9063, 
        "latency": 0.0222, 
        "openTime": 0.0250, 
        "wrRdTime": 0.0350, 
        "closeTime": 0.0184, 
        "totalTime": 0.0351
      }
, 
            {
        "access": "remove", 
        "totalTime": 0.0177
      }
]
]
, 
  "max": {
    "writeMiB": 113445.5902, 
    "writeMB": 118956.3232, 
    "readMiB": 116857.1487, 
    "readMB": 122533.6015
  }

}
]
, 
"summary": [
{
  "operation": "write", 
  "API": "POSIX", 
  "TestID": 0, 
  "ReferenceNumber": 0, 
  "segmentCount": 1, 
  "blockSize": 16777216, 
  "transferSize": 16777216, 
  "numTasks": 256, 
  "tasksPerNode": 64, 
  "repetitions": 1, 
  "filePerProc": 1, 
  "reorderTasks": 0, 
  "taskPerNodeOffset": 1, 
  "reorderTasksRandom": 0, 
  "reorderTasksRandomSeed": 0, 
  "segmentCount": 1, 
  "blockSize": 16777216, 
  "transferSize": 16777216, 
  "bwMaxMIB": 113445.5902, 
  "bwMinMIB": 113445.5902, 
  "bwMeanMIB": 113445.5902, 
  "bwStdMIB": 0.0000, 
  "OPsMax": 7090.3494, 
  "OPsMin": 7090.3494, 
  "OPsMean": 7090.3494, 
  "OPsSD": 0.0000, 
  "MeanTime": 0.0361, 
  "xsizeMiB": 4096.0000
}
, 
{
  "operation": "read", 
  "API": "POSIX", 
  "TestID": 0, 
  "ReferenceNumber": 0, 
  "segmentCount": 1, 
  "blockSize": 16777216, 
  "transferSize": 16777216, 
  "numTasks": 256, 
  "tasksPerNode": 64, 
  "repetitions": 1, 
  "filePerProc": 1, 
  "reorderTasks": 0, 
  "taskPerNodeOffset": 1, 
  "reorderTasksRandom": 0, 
  "reorderTasksRandomSeed": 0, 
  "segmentCount": 1, 
  "blockSize": 16777216, 
  "transferSize": 16777216, 
  "bwMaxMIB": 116857.1487, 
  "bwMinMIB": 116857.1487, 
  "bwMeanMIB": 116857.1487, 
  "bwStdMIB": 0.0000, 
  "OPsMax": 7303.5718, 
  "OPsMin": 7303.5718, 
  "OPsMean": 7303.5718, 
  "OPsSD": 0.0000, 
  "MeanTime": 0.0351, 
  "xsizeMiB": 4096.0000
}
]
, 
"Finished": "Fri May  2 02:33:10 2025"
}
