{
  "Version": "3.3.0", 
  "Began": "Thu May  1 11:29:41 2025", 
  "Command line": "ior -a POSIX -w -r -t 64m -b 64m -s 25 -e -F -o /dev/shm/tang584//qfs/projects/datamesh/tang584/linux_resource_detect/io_test/iortest_50gb/pior_64m_50gb_n32_2.bin -O summaryFormat=JSON -O summaryFile=pior_64m_50gb_n32_2.json", 
  "Machine": "Linux dc251.local", 
  "tests": [
    {
    "TestID": 0, 
    "StartTime": "Thu May  1 11:29:41 2025"    , "Path": "/dev/shm/tang584/qfs/projects/datamesh/tang584/linux_resource_detect/io_test/iortest_50gb","Capacity": "125.8 GiB", "Used Capacity": "0.1%","Inodes": "31.4 Mi", "Used Inodes" : "0.0%"
, 
    "Parameters": {
      "testID": 0, 
      "refnum": 0, 
      "api": "POSIX", 
      "platform": "dc251.local(Linux)", 
      "testFileName": "/dev/shm/tang584//qfs/projects/datamesh/tang584/linux_resource_detect/io_test/iortest_50gb/pior_64m_50gb_n32_2.bin", 
      "hintsFileName": "(null)", 
      "deadlineForStonewall": 0, 
      "stoneWallingWearOut": 0, 
      "maxTimeDuration": 0, 
      "outlierThreshold": 0, 
      "options": "(null)", 
      "dryRun": 0, 
      "nodes": 1, 
      "memoryPerTask": 0, 
      "memoryPerNode": 0, 
      "tasksPerNode": 32, 
      "repetitions": 1, 
      "multiFile": 0, 
      "interTestDelay": 0, 
      "fsync": 1, 
      "fsyncperwrite": 0, 
      "useExistingTestFile": 0, 
      "showHints": 0, 
      "uniqueDir": 0, 
      "individualDataSets": 0, 
      "singleXferAttempt": 0, 
      "readFile": 1, 
      "writeFile": 1, 
      "filePerProc": 1, 
      "reorderTasks": 0, 
      "reorderTasksRandom": 0, 
      "reorderTasksRandomSeed": 0, 
      "randomOffset": 0, 
      "checkWrite": 0, 
      "checkRead": 0, 
      "preallocate": 0, 
      "useFileView": 0, 
      "setAlignment": 1, 
      "storeFileOffset": 0, 
      "useSharedFilePointer": 0, 
      "useStridedDatatype": 0, 
      "keepFile": 0, 
      "keepFileWithError": 0, 
      "quitOnError": 0, 
      "verbose": 0, 
      "data packet type": "g", 
      "setTimeStampSignature/incompressibleSeed": 0, 
      "collective": 0, 
      "segmentCount": 25, 
      "transferSize": 67108864, 
      "blockSize": 67108864
    }
, 
    "Options": {
      "api": "POSIX", 
      "apiVersion": "", 
      "test filename": "/dev/shm/tang584//qfs/projects/datamesh/tang584/linux_resource_detect/io_test/iortest_50gb/pior_64m_50gb_n32_2.bin", 
      "access": "file-per-process", 
      "type": "independent", 
      "segments": 25, 
      "ordering in a file": "sequential", 
      "ordering inter file": "no tasks offsets", 
      "nodes": 1, 
      "tasks": 32, 
      "clients per node": 32, 
      "repetitions": 1, 
      "xfersize": "64 MiB", 
      "blocksize": "64 MiB", 
      "aggregate filesize": "50 GiB"
    }
, 
    "Results": [
      [             {
        "access": "write", 
        "bwMiB": 55858.4267, 
        "blockKiB": 65536.0000, 
        "xferKiB": 65536.0000, 
        "iops": 872.8736, 
        "latency": 0.8790, 
        "openTime": 0.0003, 
        "wrRdTime": 0.9165, 
        "closeTime": 0.3118, 
        "totalTime": 0.9166
      }
, 
            {
        "access": "read", 
        "bwMiB": 52803.0691, 
        "blockKiB": 65536.0000, 
        "xferKiB": 65536.0000, 
        "iops": 825.0702, 
        "latency": 0.7277, 
        "openTime": 0.0002, 
        "wrRdTime": 0.9696, 
        "closeTime": 0.5603, 
        "totalTime": 0.9696
      }
, 
            {
        "access": "remove", 
        "totalTime": 0.3715
      }
]
]
, 
  "max": {
    "writeMiB": 55858.4267, 
    "writeMB": 58571.8057, 
    "readMiB": 52803.0691, 
    "readMB": 55368.0310
  }

}
]
, 
"summary": [
{
  "operation": "write", 
  "API": "POSIX", 
  "TestID": 0, 
  "ReferenceNumber": 0, 
  "segmentCount": 25, 
  "blockSize": 67108864, 
  "transferSize": 67108864, 
  "numTasks": 32, 
  "tasksPerNode": 32, 
  "repetitions": 1, 
  "filePerProc": 1, 
  "reorderTasks": 0, 
  "taskPerNodeOffset": 1, 
  "reorderTasksRandom": 0, 
  "reorderTasksRandomSeed": 0, 
  "segmentCount": 25, 
  "blockSize": 67108864, 
  "transferSize": 67108864, 
  "bwMaxMIB": 55858.4267, 
  "bwMinMIB": 55858.4267, 
  "bwMeanMIB": 55858.4267, 
  "bwStdMIB": 0.0000, 
  "OPsMax": 872.7879, 
  "OPsMin": 872.7879, 
  "OPsMean": 872.7879, 
  "OPsSD": 0.0000, 
  "MeanTime": 0.9166, 
  "xsizeMiB": 51200.0000
}
, 
{
  "operation": "read", 
  "API": "POSIX", 
  "TestID": 0, 
  "ReferenceNumber": 0, 
  "segmentCount": 25, 
  "blockSize": 67108864, 
  "transferSize": 67108864, 
  "numTasks": 32, 
  "tasksPerNode": 32, 
  "repetitions": 1, 
  "filePerProc": 1, 
  "reorderTasks": 0, 
  "taskPerNodeOffset": 1, 
  "reorderTasksRandom": 0, 
  "reorderTasksRandomSeed": 0, 
  "segmentCount": 25, 
  "blockSize": 67108864, 
  "transferSize": 67108864, 
  "bwMaxMIB": 52803.0691, 
  "bwMinMIB": 52803.0691, 
  "bwMeanMIB": 52803.0691, 
  "bwStdMIB": 0.0000, 
  "OPsMax": 825.0480, 
  "OPsMin": 825.0480, 
  "OPsMean": 825.0480, 
  "OPsSD": 0.0000, 
  "MeanTime": 0.9696, 
  "xsizeMiB": 51200.0000
}
]
, 
"Finished": "Thu May  1 11:29:43 2025"
}
