{
  "Version": "3.3.0", 
  "Began": "Tue Dec 10 00:06:23 2024", 
  "Command line": "ior -a POSIX -w -r -t 1k -s 40 -e -F -o ///rcfs/projects/chess/tang584/iortest_5gb/pior_1k_5gb_n128_2.bin -O summaryFormat=JSON -O summaryFile=pior_1k_5gb_n128_2.json", 
  "Machine": "Linux dc193.local", 
  "tests": [
    {
    "TestID": 0, 
    "StartTime": "Tue Dec 10 00:06:23 2024"    , "Path": "/rcfs/projects/chess/tang584/iortest_5gb","Capacity": "4579.0 TiB", "Used Capacity": "80.8%","Inodes": "0.0 Mi", "Used Inodes" : "-nan%"
, 
    "Parameters": {
      "testID": 0, 
      "refnum": 0, 
      "api": "POSIX", 
      "platform": "dc193.local(Linux)", 
      "testFileName": "///rcfs/projects/chess/tang584/iortest_5gb/pior_1k_5gb_n128_2.bin", 
      "hintsFileName": "(null)", 
      "deadlineForStonewall": 0, 
      "stoneWallingWearOut": 0, 
      "maxTimeDuration": 0, 
      "outlierThreshold": 0, 
      "options": "(null)", 
      "dryRun": 0, 
      "nodes": 2, 
      "memoryPerTask": 0, 
      "memoryPerNode": 0, 
      "tasksPerNode": 64, 
      "repetitions": 1, 
      "multiFile": 0, 
      "interTestDelay": 0, 
      "fsync": 1, 
      "fsyncperwrite": 0, 
      "useExistingTestFile": 0, 
      "showHints": 0, 
      "uniqueDir": 0, 
      "individualDataSets": 0, 
      "singleXferAttempt": 0, 
      "readFile": 1, 
      "writeFile": 1, 
      "filePerProc": 1, 
      "reorderTasks": 0, 
      "reorderTasksRandom": 0, 
      "reorderTasksRandomSeed": 0, 
      "randomOffset": 0, 
      "checkWrite": 0, 
      "checkRead": 0, 
      "preallocate": 0, 
      "useFileView": 0, 
      "setAlignment": 1, 
      "storeFileOffset": 0, 
      "useSharedFilePointer": 0, 
      "useStridedDatatype": 0, 
      "keepFile": 0, 
      "keepFileWithError": 0, 
      "quitOnError": 0, 
      "verbose": 0, 
      "data packet type": "g", 
      "setTimeStampSignature/incompressibleSeed": 0, 
      "collective": 0, 
      "segmentCount": 40, 
      "transferSize": 1024, 
      "blockSize": 1048576
    }
, 
    "Options": {
      "api": "POSIX", 
      "apiVersion": "", 
      "test filename": "///rcfs/projects/chess/tang584/iortest_5gb/pior_1k_5gb_n128_2.bin", 
      "access": "file-per-process", 
      "type": "independent", 
      "segments": 40, 
      "ordering in a file": "sequential", 
      "ordering inter file": "no tasks offsets", 
      "nodes": 2, 
      "tasks": 128, 
      "clients per node": 64, 
      "repetitions": 1, 
      "xfersize": "1024 bytes", 
      "blocksize": "1 MiB", 
      "aggregate filesize": "5 GiB"
    }
, 
    "Results": [
      [             {
        "access": "write", 
        "bwMiB": 11149.4466, 
        "blockKiB": 1024.0000, 
        "xferKiB": 1.0000, 
        "iops": 11648331.9769, 
        "latency": 0.0004, 
        "openTime": 0.0436, 
        "wrRdTime": 0.4501, 
        "closeTime": 0.1148, 
        "totalTime": 0.4592
      }
, 
            {
        "access": "read", 
        "bwMiB": 17698.4241, 
        "blockKiB": 1024.0000, 
        "xferKiB": 1.0000, 
        "iops": 18348322.1115, 
        "latency": 0.0002, 
        "openTime": 0.0282, 
        "wrRdTime": 0.2857, 
        "closeTime": 0.1371, 
        "totalTime": 0.2893
      }
, 
            {
        "access": "remove", 
        "totalTime": 0.1060
      }
]
]
, 
  "max": {
    "writeMiB": 11149.4466, 
    "writeMB": 11691.0422, 
    "readMiB": 17698.4241, 
    "readMB": 18558.1427
  }

}
]
, 
"summary": [
{
  "operation": "write", 
  "API": "POSIX", 
  "TestID": 0, 
  "ReferenceNumber": 0, 
  "segmentCount": 40, 
  "blockSize": 1048576, 
  "transferSize": 1024, 
  "numTasks": 128, 
  "tasksPerNode": 64, 
  "repetitions": 1, 
  "filePerProc": 1, 
  "reorderTasks": 0, 
  "taskPerNodeOffset": 1, 
  "reorderTasksRandom": 0, 
  "reorderTasksRandomSeed": 0, 
  "segmentCount": 40, 
  "blockSize": 1048576, 
  "transferSize": 1024, 
  "bwMaxMIB": 11149.4466, 
  "bwMinMIB": 11149.4466, 
  "bwMeanMIB": 11149.4466, 
  "bwStdMIB": 0.0000, 
  "OPsMax": 11417033.3690, 
  "OPsMin": 11417033.3690, 
  "OPsMean": 11417033.3690, 
  "OPsSD": 0.0000, 
  "MeanTime": 0.4592, 
  "xsizeMiB": 5120.0000
}
, 
{
  "operation": "read", 
  "API": "POSIX", 
  "TestID": 0, 
  "ReferenceNumber": 0, 
  "segmentCount": 40, 
  "blockSize": 1048576, 
  "transferSize": 1024, 
  "numTasks": 128, 
  "tasksPerNode": 64, 
  "repetitions": 1, 
  "filePerProc": 1, 
  "reorderTasks": 0, 
  "taskPerNodeOffset": 1, 
  "reorderTasksRandom": 0, 
  "reorderTasksRandomSeed": 0, 
  "segmentCount": 40, 
  "blockSize": 1048576, 
  "transferSize": 1024, 
  "bwMaxMIB": 17698.4241, 
  "bwMinMIB": 17698.4241, 
  "bwMeanMIB": 17698.4241, 
  "bwStdMIB": 0.0000, 
  "OPsMax": 18123186.2442, 
  "OPsMin": 18123186.2442, 
  "OPsMean": 18123186.2442, 
  "OPsSD": 0.0000, 
  "MeanTime": 0.2893, 
  "xsizeMiB": 5120.0000
}
]
, 
"Finished": "Tue Dec 10 00:06:24 2024"
}
