{
  "Version": "3.3.0", 
  "Began": "Sun May  4 23:56:28 2025", 
  "Command line": "ior -a POSIX -w -r -t 4m -b 4m -s 64 -e -F -o ///rcfs/projects/chess/tang584/iortest_1gb/pior_4m_1gb_n4_2.bin -O summaryFormat=JSON -O summaryFile=pior_4m_1gb_n4_2.json", 
  "Machine": "Linux dc008.local", 
  "tests": [
    {
    "TestID": 0, 
    "StartTime": "Sun May  4 23:56:28 2025"    , "Path": "/rcfs/projects/chess/tang584/iortest_1gb","Capacity": "4579.0 TiB", "Used Capacity": "93.9%","Inodes": "0.0 Mi", "Used Inodes" : "-nan%"
, 
    "Parameters": {
      "testID": 0, 
      "refnum": 0, 
      "api": "POSIX", 
      "platform": "dc008.local(Linux)", 
      "testFileName": "///rcfs/projects/chess/tang584/iortest_1gb/pior_4m_1gb_n4_2.bin", 
      "hintsFileName": "(null)", 
      "deadlineForStonewall": 0, 
      "stoneWallingWearOut": 0, 
      "maxTimeDuration": 0, 
      "outlierThreshold": 0, 
      "options": "(null)", 
      "dryRun": 0, 
      "nodes": 1, 
      "memoryPerTask": 0, 
      "memoryPerNode": 0, 
      "tasksPerNode": 4, 
      "repetitions": 1, 
      "multiFile": 0, 
      "interTestDelay": 0, 
      "fsync": 1, 
      "fsyncperwrite": 0, 
      "useExistingTestFile": 0, 
      "showHints": 0, 
      "uniqueDir": 0, 
      "individualDataSets": 0, 
      "singleXferAttempt": 0, 
      "readFile": 1, 
      "writeFile": 1, 
      "filePerProc": 1, 
      "reorderTasks": 0, 
      "reorderTasksRandom": 0, 
      "reorderTasksRandomSeed": 0, 
      "randomOffset": 0, 
      "checkWrite": 0, 
      "checkRead": 0, 
      "preallocate": 0, 
      "useFileView": 0, 
      "setAlignment": 1, 
      "storeFileOffset": 0, 
      "useSharedFilePointer": 0, 
      "useStridedDatatype": 0, 
      "keepFile": 0, 
      "keepFileWithError": 0, 
      "quitOnError": 0, 
      "verbose": 0, 
      "data packet type": "g", 
      "setTimeStampSignature/incompressibleSeed": 0, 
      "collective": 0, 
      "segmentCount": 64, 
      "transferSize": 4194304, 
      "blockSize": 4194304
    }
, 
    "Options": {
      "api": "POSIX", 
      "apiVersion": "", 
      "test filename": "///rcfs/projects/chess/tang584/iortest_1gb/pior_4m_1gb_n4_2.bin", 
      "access": "file-per-process", 
      "type": "independent", 
      "segments": 64, 
      "ordering in a file": "sequential", 
      "ordering inter file": "no tasks offsets", 
      "nodes": 1, 
      "tasks": 4, 
      "clients per node": 4, 
      "repetitions": 1, 
      "xfersize": "4 MiB", 
      "blocksize": "4 MiB", 
      "aggregate filesize": "1 GiB"
    }
, 
    "Results": [
      [             {
        "access": "write", 
        "bwMiB": 6128.5945, 
        "blockKiB": 4096.0000, 
        "xferKiB": 4096.0000, 
        "iops": 1572.9387, 
        "latency": 0.1599, 
        "openTime": 0.0146, 
        "wrRdTime": 0.1628, 
        "closeTime": 0.0074, 
        "totalTime": 0.1671
      }
, 
            {
        "access": "read", 
        "bwMiB": 5405.3927, 
        "blockKiB": 4096.0000, 
        "xferKiB": 4096.0000, 
        "iops": 1362.5508, 
        "latency": 0.1829, 
        "openTime": 0.0004, 
        "wrRdTime": 0.1879, 
        "closeTime": 0.0092, 
        "totalTime": 0.1894
      }
, 
            {
        "access": "remove", 
        "totalTime": 0.0031
      }
]
]
, 
  "max": {
    "writeMiB": 6128.5945, 
    "writeMB": 6426.2971, 
    "readMiB": 5405.3927, 
    "readMB": 5667.9650
  }

}
]
, 
"summary": [
{
  "operation": "write", 
  "API": "POSIX", 
  "TestID": 0, 
  "ReferenceNumber": 0, 
  "segmentCount": 64, 
  "blockSize": 4194304, 
  "transferSize": 4194304, 
  "numTasks": 4, 
  "tasksPerNode": 4, 
  "repetitions": 1, 
  "filePerProc": 1, 
  "reorderTasks": 0, 
  "taskPerNodeOffset": 1, 
  "reorderTasksRandom": 0, 
  "reorderTasksRandomSeed": 0, 
  "segmentCount": 64, 
  "blockSize": 4194304, 
  "transferSize": 4194304, 
  "bwMaxMIB": 6128.5945, 
  "bwMinMIB": 6128.5945, 
  "bwMeanMIB": 6128.5945, 
  "bwStdMIB": 0.0000, 
  "OPsMax": 1532.1486, 
  "OPsMin": 1532.1486, 
  "OPsMean": 1532.1486, 
  "OPsSD": 0.0000, 
  "MeanTime": 0.1671, 
  "xsizeMiB": 1024.0000
}
, 
{
  "operation": "read", 
  "API": "POSIX", 
  "TestID": 0, 
  "ReferenceNumber": 0, 
  "segmentCount": 64, 
  "blockSize": 4194304, 
  "transferSize": 4194304, 
  "numTasks": 4, 
  "tasksPerNode": 4, 
  "repetitions": 1, 
  "filePerProc": 1, 
  "reorderTasks": 0, 
  "taskPerNodeOffset": 1, 
  "reorderTasksRandom": 0, 
  "reorderTasksRandomSeed": 0, 
  "segmentCount": 64, 
  "blockSize": 4194304, 
  "transferSize": 4194304, 
  "bwMaxMIB": 5405.3927, 
  "bwMinMIB": 5405.3927, 
  "bwMeanMIB": 5405.3927, 
  "bwStdMIB": 0.0000, 
  "OPsMax": 1351.3482, 
  "OPsMin": 1351.3482, 
  "OPsMean": 1351.3482, 
  "OPsSD": 0.0000, 
  "MeanTime": 0.1894, 
  "xsizeMiB": 1024.0000
}
]
, 
"Finished": "Sun May  4 23:56:28 2025"
}
