{
  "Version": "3.3.0", 
  "Began": "Mon May  5 04:59:47 2025", 
  "Command line": "ior -a POSIX -w -r -t 1m -b 1m -s 400 -e -F -o ///rcfs/projects/chess/tang584/iortest_50gb/pior_1m_50gb_n128_1.bin -O summaryFormat=JSON -O summaryFile=pior_1m_50gb_n128_1.json", 
  "Machine": "Linux dc008.local", 
  "tests": [
    {
    "TestID": 0, 
    "StartTime": "Mon May  5 04:59:47 2025"    , "Path": "/rcfs/projects/chess/tang584/iortest_50gb","Capacity": "4579.0 TiB", "Used Capacity": "93.9%","Inodes": "0.0 Mi", "Used Inodes" : "-nan%"
, 
    "Parameters": {
      "testID": 0, 
      "refnum": 0, 
      "api": "POSIX", 
      "platform": "dc008.local(Linux)", 
      "testFileName": "///rcfs/projects/chess/tang584/iortest_50gb/pior_1m_50gb_n128_1.bin", 
      "hintsFileName": "(null)", 
      "deadlineForStonewall": 0, 
      "stoneWallingWearOut": 0, 
      "maxTimeDuration": 0, 
      "outlierThreshold": 0, 
      "options": "(null)", 
      "dryRun": 0, 
      "nodes": 1, 
      "memoryPerTask": 0, 
      "memoryPerNode": 0, 
      "tasksPerNode": 128, 
      "repetitions": 1, 
      "multiFile": 0, 
      "interTestDelay": 0, 
      "fsync": 1, 
      "fsyncperwrite": 0, 
      "useExistingTestFile": 0, 
      "showHints": 0, 
      "uniqueDir": 0, 
      "individualDataSets": 0, 
      "singleXferAttempt": 0, 
      "readFile": 1, 
      "writeFile": 1, 
      "filePerProc": 1, 
      "reorderTasks": 0, 
      "reorderTasksRandom": 0, 
      "reorderTasksRandomSeed": 0, 
      "randomOffset": 0, 
      "checkWrite": 0, 
      "checkRead": 0, 
      "preallocate": 0, 
      "useFileView": 0, 
      "setAlignment": 1, 
      "storeFileOffset": 0, 
      "useSharedFilePointer": 0, 
      "useStridedDatatype": 0, 
      "keepFile": 0, 
      "keepFileWithError": 0, 
      "quitOnError": 0, 
      "verbose": 0, 
      "data packet type": "g", 
      "setTimeStampSignature/incompressibleSeed": 0, 
      "collective": 0, 
      "segmentCount": 400, 
      "transferSize": 1048576, 
      "blockSize": 1048576
    }
, 
    "Options": {
      "api": "POSIX", 
      "apiVersion": "", 
      "test filename": "///rcfs/projects/chess/tang584/iortest_50gb/pior_1m_50gb_n128_1.bin", 
      "access": "file-per-process", 
      "type": "independent", 
      "segments": 400, 
      "ordering in a file": "sequential", 
      "ordering inter file": "no tasks offsets", 
      "nodes": 1, 
      "tasks": 128, 
      "clients per node": 128, 
      "repetitions": 1, 
      "xfersize": "1 MiB", 
      "blocksize": "1 MiB", 
      "aggregate filesize": "50 GiB"
    }
, 
    "Results": [
      [             {
        "access": "write", 
        "bwMiB": 4321.4739, 
        "blockKiB": 1024.0000, 
        "xferKiB": 1024.0000, 
        "iops": 4337.3675, 
        "latency": 11.2770, 
        "openTime": 0.1935, 
        "wrRdTime": 11.8044, 
        "closeTime": 0.5842, 
        "totalTime": 11.8478
      }
, 
            {
        "access": "read", 
        "bwMiB": 4044.2371, 
        "blockKiB": 1024.0000, 
        "xferKiB": 1024.0000, 
        "iops": 4058.3905, 
        "latency": 12.3890, 
        "openTime": 0.6870, 
        "wrRdTime": 12.6158, 
        "closeTime": 0.5466, 
        "totalTime": 12.6600
      }
, 
            {
        "access": "remove", 
        "totalTime": 0.0661
      }
]
]
, 
  "max": {
    "writeMiB": 4321.4739, 
    "writeMB": 4531.3938, 
    "readMiB": 4044.2371, 
    "readMB": 4240.6900
  }

}
]
, 
"summary": [
{
  "operation": "write", 
  "API": "POSIX", 
  "TestID": 0, 
  "ReferenceNumber": 0, 
  "segmentCount": 400, 
  "blockSize": 1048576, 
  "transferSize": 1048576, 
  "numTasks": 128, 
  "tasksPerNode": 128, 
  "repetitions": 1, 
  "filePerProc": 1, 
  "reorderTasks": 0, 
  "taskPerNodeOffset": 1, 
  "reorderTasksRandom": 0, 
  "reorderTasksRandomSeed": 0, 
  "segmentCount": 400, 
  "blockSize": 1048576, 
  "transferSize": 1048576, 
  "bwMaxMIB": 4321.4739, 
  "bwMinMIB": 4321.4739, 
  "bwMeanMIB": 4321.4739, 
  "bwStdMIB": 0.0000, 
  "OPsMax": 4321.4739, 
  "OPsMin": 4321.4739, 
  "OPsMean": 4321.4739, 
  "OPsSD": 0.0000, 
  "MeanTime": 11.8478, 
  "xsizeMiB": 51200.0000
}
, 
{
  "operation": "read", 
  "API": "POSIX", 
  "TestID": 0, 
  "ReferenceNumber": 0, 
  "segmentCount": 400, 
  "blockSize": 1048576, 
  "transferSize": 1048576, 
  "numTasks": 128, 
  "tasksPerNode": 128, 
  "repetitions": 1, 
  "filePerProc": 1, 
  "reorderTasks": 0, 
  "taskPerNodeOffset": 1, 
  "reorderTasksRandom": 0, 
  "reorderTasksRandomSeed": 0, 
  "segmentCount": 400, 
  "blockSize": 1048576, 
  "transferSize": 1048576, 
  "bwMaxMIB": 4044.2371, 
  "bwMinMIB": 4044.2371, 
  "bwMeanMIB": 4044.2371, 
  "bwStdMIB": 0.0000, 
  "OPsMax": 4044.2371, 
  "OPsMin": 4044.2371, 
  "OPsMean": 4044.2371, 
  "OPsSD": 0.0000, 
  "MeanTime": 12.6600, 
  "xsizeMiB": 51200.0000
}
]
, 
"Finished": "Mon May  5 05:00:11 2025"
}
