{
  "Version": "3.3.0", 
  "Began": "Mon Dec  9 19:31:01 2024", 
  "Command line": "ior -a POSIX -w -r -t 1k -s 3200 -e -F -o ///rcfs/projects/chess/tang584/iortest_50gb/pior_1k_50gb_n16_1.bin -O summaryFormat=JSON -O summaryFile=pior_1k_50gb_n16_1.json", 
  "Machine": "Linux dc193.local", 
  "tests": [
    {
    "TestID": 0, 
    "StartTime": "Mon Dec  9 19:31:01 2024"    , "Path": "/rcfs/projects/chess/tang584/iortest_50gb","Capacity": "4579.0 TiB", "Used Capacity": "80.8%","Inodes": "0.0 Mi", "Used Inodes" : "-nan%"
, 
    "Parameters": {
      "testID": 0, 
      "refnum": 0, 
      "api": "POSIX", 
      "platform": "dc193.local(Linux)", 
      "testFileName": "///rcfs/projects/chess/tang584/iortest_50gb/pior_1k_50gb_n16_1.bin", 
      "hintsFileName": "(null)", 
      "deadlineForStonewall": 0, 
      "stoneWallingWearOut": 0, 
      "maxTimeDuration": 0, 
      "outlierThreshold": 0, 
      "options": "(null)", 
      "dryRun": 0, 
      "nodes": 16, 
      "memoryPerTask": 0, 
      "memoryPerNode": 0, 
      "tasksPerNode": 1, 
      "repetitions": 1, 
      "multiFile": 0, 
      "interTestDelay": 0, 
      "fsync": 1, 
      "fsyncperwrite": 0, 
      "useExistingTestFile": 0, 
      "showHints": 0, 
      "uniqueDir": 0, 
      "individualDataSets": 0, 
      "singleXferAttempt": 0, 
      "readFile": 1, 
      "writeFile": 1, 
      "filePerProc": 1, 
      "reorderTasks": 0, 
      "reorderTasksRandom": 0, 
      "reorderTasksRandomSeed": 0, 
      "randomOffset": 0, 
      "checkWrite": 0, 
      "checkRead": 0, 
      "preallocate": 0, 
      "useFileView": 0, 
      "setAlignment": 1, 
      "storeFileOffset": 0, 
      "useSharedFilePointer": 0, 
      "useStridedDatatype": 0, 
      "keepFile": 0, 
      "keepFileWithError": 0, 
      "quitOnError": 0, 
      "verbose": 0, 
      "data packet type": "g", 
      "setTimeStampSignature/incompressibleSeed": 0, 
      "collective": 0, 
      "segmentCount": 3200, 
      "transferSize": 1024, 
      "blockSize": 1048576
    }
, 
    "Options": {
      "api": "POSIX", 
      "apiVersion": "", 
      "test filename": "///rcfs/projects/chess/tang584/iortest_50gb/pior_1k_50gb_n16_1.bin", 
      "access": "file-per-process", 
      "type": "independent", 
      "segments": 3200, 
      "ordering in a file": "sequential", 
      "ordering inter file": "no tasks offsets", 
      "nodes": 16, 
      "tasks": 16, 
      "clients per node": 1, 
      "repetitions": 1, 
      "xfersize": "1024 bytes", 
      "blocksize": "1 MiB", 
      "aggregate filesize": "50 GiB"
    }
, 
    "Results": [
      [             {
        "access": "write", 
        "bwMiB": 10265.6310, 
        "blockKiB": 1024.0000, 
        "xferKiB": 1.0000, 
        "iops": 10520038.1409, 
        "latency": 0.0044, 
        "openTime": 0.0039, 
        "wrRdTime": 4.9837, 
        "closeTime": 0.6115, 
        "totalTime": 4.9875
      }
, 
            {
        "access": "read", 
        "bwMiB": 9522.7811, 
        "blockKiB": 1024.0000, 
        "xferKiB": 1.0000, 
        "iops": 9753302.2312, 
        "latency": 0.0051, 
        "openTime": 0.0007, 
        "wrRdTime": 5.3755, 
        "closeTime": 0.8762, 
        "totalTime": 5.3766
      }
, 
            {
        "access": "remove", 
        "totalTime": 0.0034
      }
]
]
, 
  "max": {
    "writeMiB": 10265.6310, 
    "writeMB": 10764.2943, 
    "readMiB": 9522.7811, 
    "readMB": 9985.3597
  }

}
]
, 
"summary": [
{
  "operation": "write", 
  "API": "POSIX", 
  "TestID": 0, 
  "ReferenceNumber": 0, 
  "segmentCount": 3200, 
  "blockSize": 1048576, 
  "transferSize": 1024, 
  "numTasks": 16, 
  "tasksPerNode": 1, 
  "repetitions": 1, 
  "filePerProc": 1, 
  "reorderTasks": 0, 
  "taskPerNodeOffset": 1, 
  "reorderTasksRandom": 0, 
  "reorderTasksRandomSeed": 0, 
  "segmentCount": 3200, 
  "blockSize": 1048576, 
  "transferSize": 1024, 
  "bwMaxMIB": 10265.6310, 
  "bwMinMIB": 10265.6310, 
  "bwMeanMIB": 10265.6310, 
  "bwStdMIB": 0.0000, 
  "OPsMax": 10512006.1541, 
  "OPsMin": 10512006.1541, 
  "OPsMean": 10512006.1541, 
  "OPsSD": 0.0000, 
  "MeanTime": 4.9875, 
  "xsizeMiB": 51200.0000
}
, 
{
  "operation": "read", 
  "API": "POSIX", 
  "TestID": 0, 
  "ReferenceNumber": 0, 
  "segmentCount": 3200, 
  "blockSize": 1048576, 
  "transferSize": 1024, 
  "numTasks": 16, 
  "tasksPerNode": 1, 
  "repetitions": 1, 
  "filePerProc": 1, 
  "reorderTasks": 0, 
  "taskPerNodeOffset": 1, 
  "reorderTasksRandom": 0, 
  "reorderTasksRandomSeed": 0, 
  "segmentCount": 3200, 
  "blockSize": 1048576, 
  "transferSize": 1024, 
  "bwMaxMIB": 9522.7811, 
  "bwMinMIB": 9522.7811, 
  "bwMeanMIB": 9522.7811, 
  "bwStdMIB": 0.0000, 
  "OPsMax": 9751327.8380, 
  "OPsMin": 9751327.8380, 
  "OPsMean": 9751327.8380, 
  "OPsSD": 0.0000, 
  "MeanTime": 5.3766, 
  "xsizeMiB": 51200.0000
}
]
, 
"Finished": "Mon Dec  9 19:31:11 2024"
}
