{
  "Version": "3.3.0", 
  "Began": "Tue Jan 14 17:56:03 2025", 
  "Command line": "ior -a POSIX -w -r -t 1m -b 1m -s 2 -e -F -o ///rcfs/projects/chess/tang584/iortest_1gb/pior_1m_1gb_n512_3.bin -O summaryFormat=JSON -O summaryFile=pior_1m_1gb_n512_3.json", 
  "Machine": "Linux dc011.local", 
  "tests": [
    {
    "TestID": 0, 
    "StartTime": "Tue Jan 14 17:56:03 2025"    , "Path": "/rcfs/projects/chess/tang584/iortest_1gb","Capacity": "4579.0 TiB", "Used Capacity": "82.1%","Inodes": "0.0 Mi", "Used Inodes" : "-nan%"
, 
    "Parameters": {
      "testID": 0, 
      "refnum": 0, 
      "api": "POSIX", 
      "platform": "dc011.local(Linux)", 
      "testFileName": "///rcfs/projects/chess/tang584/iortest_1gb/pior_1m_1gb_n512_3.bin", 
      "hintsFileName": "(null)", 
      "deadlineForStonewall": 0, 
      "stoneWallingWearOut": 0, 
      "maxTimeDuration": 0, 
      "outlierThreshold": 0, 
      "options": "(null)", 
      "dryRun": 0, 
      "nodes": 4, 
      "memoryPerTask": 0, 
      "memoryPerNode": 0, 
      "tasksPerNode": 128, 
      "repetitions": 1, 
      "multiFile": 0, 
      "interTestDelay": 0, 
      "fsync": 1, 
      "fsyncperwrite": 0, 
      "useExistingTestFile": 0, 
      "showHints": 0, 
      "uniqueDir": 0, 
      "individualDataSets": 0, 
      "singleXferAttempt": 0, 
      "readFile": 1, 
      "writeFile": 1, 
      "filePerProc": 1, 
      "reorderTasks": 0, 
      "reorderTasksRandom": 0, 
      "reorderTasksRandomSeed": 0, 
      "randomOffset": 0, 
      "checkWrite": 0, 
      "checkRead": 0, 
      "preallocate": 0, 
      "useFileView": 0, 
      "setAlignment": 1, 
      "storeFileOffset": 0, 
      "useSharedFilePointer": 0, 
      "useStridedDatatype": 0, 
      "keepFile": 0, 
      "keepFileWithError": 0, 
      "quitOnError": 0, 
      "verbose": 0, 
      "data packet type": "g", 
      "setTimeStampSignature/incompressibleSeed": 0, 
      "collective": 0, 
      "segmentCount": 2, 
      "transferSize": 1048576, 
      "blockSize": 1048576
    }
, 
    "Options": {
      "api": "POSIX", 
      "apiVersion": "", 
      "test filename": "///rcfs/projects/chess/tang584/iortest_1gb/pior_1m_1gb_n512_3.bin", 
      "access": "file-per-process", 
      "type": "independent", 
      "segments": 2, 
      "ordering in a file": "sequential", 
      "ordering inter file": "no tasks offsets", 
      "nodes": 4, 
      "tasks": 512, 
      "clients per node": 128, 
      "repetitions": 1, 
      "xfersize": "1 MiB", 
      "blocksize": "1 MiB", 
      "aggregate filesize": "1 GiB"
    }
, 
    "Results": [
      [             {
        "access": "write", 
        "bwMiB": 4418.5831, 
        "blockKiB": 1024.0000, 
        "xferKiB": 1024.0000, 
        "iops": 5080.5377, 
        "latency": 0.0024, 
        "openTime": 0.2187, 
        "wrRdTime": 0.2016, 
        "closeTime": 0.2084, 
        "totalTime": 0.2317
      }
, 
            {
        "access": "read", 
        "bwMiB": 6820.9350, 
        "blockKiB": 1024.0000, 
        "xferKiB": 1024.0000, 
        "iops": 7884.4771, 
        "latency": 0.0035, 
        "openTime": 0.1369, 
        "wrRdTime": 0.1299, 
        "closeTime": 0.1377, 
        "totalTime": 0.1501
      }
, 
            {
        "access": "remove", 
        "totalTime": 0.2886
      }
]
]
, 
  "max": {
    "writeMiB": 4418.5831, 
    "writeMB": 4633.2202, 
    "readMiB": 6820.9350, 
    "readMB": 7152.2687
  }

}
]
, 
"summary": [
{
  "operation": "write", 
  "API": "POSIX", 
  "TestID": 0, 
  "ReferenceNumber": 0, 
  "segmentCount": 2, 
  "blockSize": 1048576, 
  "transferSize": 1048576, 
  "numTasks": 512, 
  "tasksPerNode": 128, 
  "repetitions": 1, 
  "filePerProc": 1, 
  "reorderTasks": 0, 
  "taskPerNodeOffset": 1, 
  "reorderTasksRandom": 0, 
  "reorderTasksRandomSeed": 0, 
  "segmentCount": 2, 
  "blockSize": 1048576, 
  "transferSize": 1048576, 
  "bwMaxMIB": 4418.5831, 
  "bwMinMIB": 4418.5831, 
  "bwMeanMIB": 4418.5831, 
  "bwStdMIB": 0.0000, 
  "OPsMax": 4418.5831, 
  "OPsMin": 4418.5831, 
  "OPsMean": 4418.5831, 
  "OPsSD": 0.0000, 
  "MeanTime": 0.2317, 
  "xsizeMiB": 1024.0000
}
, 
{
  "operation": "read", 
  "API": "POSIX", 
  "TestID": 0, 
  "ReferenceNumber": 0, 
  "segmentCount": 2, 
  "blockSize": 1048576, 
  "transferSize": 1048576, 
  "numTasks": 512, 
  "tasksPerNode": 128, 
  "repetitions": 1, 
  "filePerProc": 1, 
  "reorderTasks": 0, 
  "taskPerNodeOffset": 1, 
  "reorderTasksRandom": 0, 
  "reorderTasksRandomSeed": 0, 
  "segmentCount": 2, 
  "blockSize": 1048576, 
  "transferSize": 1048576, 
  "bwMaxMIB": 6820.9350, 
  "bwMinMIB": 6820.9350, 
  "bwMeanMIB": 6820.9350, 
  "bwStdMIB": 0.0000, 
  "OPsMax": 6820.9350, 
  "OPsMin": 6820.9350, 
  "OPsMean": 6820.9350, 
  "OPsSD": 0.0000, 
  "MeanTime": 0.1501, 
  "xsizeMiB": 1024.0000
}
]
, 
"Finished": "Tue Jan 14 17:56:05 2025"
}
